thread_notebook/__init__.py
thread_notebook/thread_notebook_app.py
thread_notebook/static/404.html
thread_notebook/static/favicon.ico
thread_notebook/static/favicon.png
thread_notebook/static/index.html
thread_notebook/static/jupyter-vega.js
thread_notebook/static/plotly.js
thread_notebook/static/require.2.3.4.min.js
thread_notebook/static/_next/static/5AxoAZSH0Szss8V2yD0cf/_buildManifest.js
thread_notebook/static/_next/static/5AxoAZSH0Szss8V2yD0cf/_ssgManifest.js
thread_notebook/static/_next/static/chunks/175675d1-c5b8377260dcdd9f.js
thread_notebook/static/_next/static/chunks/1c47faa5-29b30a7c175f080a.js
thread_notebook/static/_next/static/chunks/293.14a4f8f957b31dac.js
thread_notebook/static/_next/static/chunks/433.af5bec765f572109.js
thread_notebook/static/_next/static/chunks/4ad82c5e-e6d167e7317439ef.js
thread_notebook/static/_next/static/chunks/67a3bf3c-12526f99ad5bdc5c.js
thread_notebook/static/_next/static/chunks/735-d75b80b442c04923.js
thread_notebook/static/_next/static/chunks/74.d0181866c39f9037.js
thread_notebook/static/_next/static/chunks/966.f6b0c3d8ccb86bcd.js
thread_notebook/static/_next/static/chunks/974.c95a7184491b8b98.js
thread_notebook/static/_next/static/chunks/b14184db-22f2625587f9154a.js
thread_notebook/static/_next/static/chunks/b5f2ed29-62096d192c934d6a.js
thread_notebook/static/_next/static/chunks/b637e9a5.ebfee6b48b492480.js
thread_notebook/static/_next/static/chunks/bd65aaa0.1b370fa161a46ddf.js
thread_notebook/static/_next/static/chunks/blueprint-icons-16px-paths.cafeb7addf8b70cb.js
thread_notebook/static/_next/static/chunks/blueprint-icons-20px-paths.78cc20de364964bb.js
thread_notebook/static/_next/static/chunks/blueprint-icons-all-paths-loader.24482ba97c99bd58.js
thread_notebook/static/_next/static/chunks/blueprint-icons-all-paths.7adb212771ee800f.js
thread_notebook/static/_next/static/chunks/blueprint-icons-split-paths-by-size-loader.3e8b8c7783175318.js
thread_notebook/static/_next/static/chunks/framework-e952fed463eb8e34.js
thread_notebook-0.1.36.dist-info/METADATA
thread_notebook-0.1.36.dist-info/WHEEL
thread_notebook-0.1.36.dist-info/entry_points.txt
thread_notebook-0.1.36.dist-info/top_level.txt
thread_notebook-0.1.36.dist-info/RECORD
