Metadata-Version: 2.1
Name: thread-notebook
Version: 0.1.36
Requires-Dist: jupyter-server >=2.0
Requires-Dist: jupyter
